broadcasts/__init__.py
broadcasts/admin.py
broadcasts/context_processors.py
broadcasts/forms.py
broadcasts/managers.py
broadcasts/models.py
broadcasts/migrations/0001_initial.py
broadcasts/migrations/__init__.py
django_site_broadcasts-0.2.0.dist-info/DESCRIPTION.rst
django_site_broadcasts-0.2.0.dist-info/METADATA
django_site_broadcasts-0.2.0.dist-info/RECORD
django_site_broadcasts-0.2.0.dist-info/WHEEL
django_site_broadcasts-0.2.0.dist-info/metadata.json
django_site_broadcasts-0.2.0.dist-info/top_level.txt
