Metadata-Version: 2.0
Name: django-site-broadcasts
Version: 0.2.0
Summary: A small Django app that displays temporary, short broadcasts across a site.
Home-page: https://github.com/bennylope/django-site-broadcasts/
Author: Ben Lopatin
Author-email: ben@benlopatin.com
License: BSD License
Platform: OS Independent
Classifier: Development Status :: 4 - Beta
Classifier: Environment :: Web Environment
Classifier: Intended Audience :: Developers
Classifier: License :: OSI Approved :: BSD License
Classifier: Operating System :: OS Independent
Classifier: Programming Language :: Python
Classifier: Programming Language :: Python :: 2.7
Classifier: Programming Language :: Python :: 3.4
Classifier: Programming Language :: Python :: 3.5
Classifier: Programming Language :: Python :: 3.6
Classifier: Programming Language :: Python :: Implementation :: CPython
Classifier: Framework :: Django
Requires-Dist: Django (>=1.8)
